MANIFEST.in
setup.py
dj_markdown/__init__.py
dj_markdown.egg-info/PKG-INFO
dj_markdown.egg-info/SOURCES.txt
dj_markdown.egg-info/dependency_links.txt
dj_markdown.egg-info/not-zip-safe
dj_markdown.egg-info/requires.txt
dj_markdown.egg-info/top_level.txt
dj_markdown/static/.DS_Store
dj_markdown/static/dj_markdown/css/styles/agate.css
dj_markdown/static/dj_markdown/css/styles/androidstudio.css
dj_markdown/static/dj_markdown/css/styles/arduino-light.css
dj_markdown/static/dj_markdown/css/styles/arta.css
dj_markdown/static/dj_markdown/css/styles/ascetic.css
dj_markdown/static/dj_markdown/css/styles/atelier-cave-dark.css
dj_markdown/static/dj_markdown/css/styles/atelier-cave-light.css
dj_markdown/static/dj_markdown/css/styles/atelier-dune-dark.css
dj_markdown/static/dj_markdown/css/styles/atelier-dune-light.css
dj_markdown/static/dj_markdown/css/styles/atelier-estuary-dark.css
dj_markdown/static/dj_markdown/css/styles/atelier-estuary-light.css
dj_markdown/static/dj_markdown/css/styles/atelier-forest-dark.css
dj_markdown/static/dj_markdown/css/styles/atelier-forest-light.css
dj_markdown/static/dj_markdown/css/styles/atelier-heath-dark.css
dj_markdown/static/dj_markdown/css/styles/atelier-heath-light.css
dj_markdown/static/dj_markdown/css/styles/atelier-lakeside-dark.css
dj_markdown/static/dj_markdown/css/styles/atelier-lakeside-light.css
dj_markdown/static/dj_markdown/css/styles/atelier-plateau-dark.css
dj_markdown/static/dj_markdown/css/styles/atelier-plateau-light.css
dj_markdown/static/dj_markdown/css/styles/atelier-savanna-dark.css
dj_markdown/static/dj_markdown/css/styles/atelier-savanna-light.css
dj_markdown/static/dj_markdown/css/styles/atelier-seaside-dark.css
dj_markdown/static/dj_markdown/css/styles/atelier-seaside-light.css
dj_markdown/static/dj_markdown/css/styles/atelier-sulphurpool-dark.css
dj_markdown/static/dj_markdown/css/styles/atelier-sulphurpool-light.css
dj_markdown/static/dj_markdown/css/styles/atom-one-dark.css
dj_markdown/static/dj_markdown/css/styles/atom-one-light.css
dj_markdown/static/dj_markdown/css/styles/brown-paper.css
dj_markdown/static/dj_markdown/css/styles/codepen-embed.css
dj_markdown/static/dj_markdown/css/styles/color-brewer.css
