Metadata-Version: 1.1
Name: dj-markdown
Version: 0.1.2
Summary: Django Markdown custom plugin and template tags
Home-page: https://github.com/CarlosMart626/dj_markdown
Author: Carlos Martínez
Author-email: carlosmart626@gmail.com
License: MIT License
Keywords: django markdown templatetags code highlight
Platform: OS Independent
Classifier: Development Status :: 4 - Beta
Classifier: Environment :: Web Environment
Classifier: Framework :: Django
Classifier: Intended Audience :: Developers
Classifier: License :: OSI Approved :: MIT License
Classifier: Operating System :: OS Independent
Classifier: Programming Language :: Python
Classifier: Programming Language :: Python :: 2.6
Classifier: Programming Language :: Python :: 2.7
Classifier: Programming Language :: Python :: 3.5
Classifier: Programming Language :: Python :: 3.6
